smemo/__init__.py
smemo/py.typed
smemo-0.7.dist-info/LICENSE
smemo-0.7.dist-info/METADATA
smemo-0.7.dist-info/WHEEL
smemo-0.7.dist-info/top_level.txt
smemo-0.7.dist-info/RECORD
