Metadata-Version: 2.1
Name: smemo
Version: 0.7
Summary: Explicit session memoization
Home-page: https://github.com/isaacto/smemo
Author: Isaac To
Author-email: isaac.to@gmail.com
Classifier: Development Status :: 4 - Beta
Classifier: Programming Language :: Python :: 3.5
Classifier: Programming Language :: Python :: 3.6
Classifier: Programming Language :: Python :: 3.7
Classifier: Programming Language :: Python :: 3.8
Classifier: Topic :: Software Development :: Libraries
Classifier: License :: OSI Approved :: MIT License
Classifier: Operating System :: OS Independent
Requires-Python: ~=3.5
License-File: LICENSE
